LICENSE
README.md
setup.py
CVE_2019_9670.egg-info/PKG-INFO
CVE_2019_9670.egg-info/SOURCES.txt
CVE_2019_9670.egg-info/dependency_links.txt
CVE_2019_9670.egg-info/entry_points.txt
CVE_2019_9670.egg-info/requires.txt
CVE_2019_9670.egg-info/top_level.txt
cve20199670/__init__.py
cve20199670/main.py
cve20199670/includes/__init__.py
cve20199670/includes/bot.py
cve20199670/includes/filereader.py
cve20199670/includes/scan.py
cve20199670/includes/writefile.py
cve20199670/utils/__init__.py
cve20199670/utils/configure.py
cve20199670/utils/const.py
cve20199670/utils/helpers.py
cve20199670/utils/status.py